{
  "cables": {
    "Ruddy": {
      "Tipo": "ACSR",
      "mecanicas": {
        "Tamaño_kcmil": "900.0",
        "Trenzado_Al": "45x0.1414",
        "Trenzado_Acero": "7x0.0943",
        "Seccion_Total_sqin": "0.7555",
        "Seccion_Al_sqin": "0.7066",
        "Diametro_Exterior_in": "1.131",
        "Peso_Total_lbs_kft": "1013",
        "Peso_Al_lbs_kft": "847.9",
        "Peso_Acero_lbs_kft": "165.6",
        "Porcentaje_Peso_Al_lbs_kft": "83.70%",
        "Porcentaje_Peso_Acero_lbs_kft": "16.35%",
        "Resistencia_GA2_lbs": "24400",
        "Resistencia_GA3_HS_lbs": "25400",
        "Resistencia_GA5_UHS_lbs": "26300"
      },
      "electricas": {
        "Tamaño_kcmil": "900.0",
        "Trenzado_Al": "45x0.1414",
        "Trenzado_Acero": "7x0.0943",
        "Seccion_Total_sqin": "0.7555",
        "Seccion_Al_sqin": "0.7066",
        "Diametro_Exterior_in": "1.131",
        "Resistencia_DC_20C_ohm_kft": "0.0191",
        "Resistencia_AC_25C_ohm_kft": "0.0200",
        "Resistencia_AC_75C_ohm_kft": "0.0246",
        "Ampacidad_75C_STD_ohm_kft": "940",
        "Ampacidad_75C_EX3": "1080",
        "Radio_Medio_Generico_ft": "0.0373",
        "Reactancia_Industrial_ohm_kft": "0.0756",
        "Reactancia_Capacitiva_Mohm_kft": "0.4755"
      }
    },
    "Canary": {
      "Tipo": "ACSR",
      "mecanicas": {
        "Tamaño_kcmil": "900.0",
        "Trenzado_Al": "54x0.1291",
        "Trenzado_Acero": "7x0.1291",
        "Seccion_Total_sqin": "0.7985",
        "Seccion_Al_sqin": "0.7089",
        "Diametro_Exterior_in": "1.162",
        "Peso_Total_lbs_kft": "1160",
        "Peso_Al_lbs_kft": "849.4",
        "Peso_Acero_lbs_kft": "310.4",
        "Porcentaje_Peso_Al_lbs_kft": "73.22%",
        "Porcentaje_Peso_Acero_lbs_kft": "26.76%",
        "Resistencia_GA2_lbs": "31900",
        "Resistencia_GA3_HS_lbs": "33700",
        "Resistencia_GA5_UHS_lbs": "35400"
      },
      "electricas": {
        "Tamaño_kcmil": "900.0",
        "Trenzado_Al": "54x0.1291",
        "Trenzado_Acero": "7x0.1291",
        "Seccion_Total_sqin": "0.7985",
        "Seccion_Al_sqin": "0.7089",
        "Diametro_Exterior_in": "1.162",
        "Resistencia_DC_20C_ohm_kft": "0.0190",
        "Resistencia_AC_25C_ohm_kft": "0.0198",
        "Resistencia_AC_75C_ohm_kft": "0.0244",
        "Ampacidad_75C_STD_ohm_kft": "955",
        "Ampacidad_75C_EX3": "1095",
        "Radio_Medio_Generico_ft": "0.0390",
        "Reactancia_Industrial_ohm_kft": "0.0746",
        "Reactancia_Capacitiva_Mohm_kft": "0.4743"
      }
    },
    "Catbird": {
      "Tipo": "ACSR",
      "mecanicas": {
        "Tamaño_kcmil": "954.0",
        "Trenzado_Al": "36x0.1628",
        "Trenzado_Acero": "1x0.1628",
        "Seccion_Total_sqin": "0.7702",
        "Seccion_Al_sqin": "0.7494",
        "Diametro_Exterior_in": "1.140",
        "Peso_Total_lbs_kft": "986",
        "Peso_Al_lbs_kft": "885.4",
        "Peso_Acero_lbs_kft": "70.2",
        "Porcentaje_Peso_Al_lbs_kft": "82.73%",
        "Porcentaje_Peso_Acero_lbs_kft": "7.27%",
        "Resistencia_GA2_lbs": "19800",
        "Resistencia_GA3_HS_lbs": "20300",
        "Resistencia_GA5_UHS_lbs": "20700"
      },
      "electricas": {
        "Tamaño_kcmil": "954.0",
        "Trenzado_Al": "36x0.1628",
        "Trenzado_Acero": "1x0.1628",
        "Seccion_Total_sqin": "0.7702",
        "Seccion_Al_sqin": "0.7494",
        "Diametro_Exterior_in": "1.140",
        "Resistencia_DC_20C_ohm_kft": "0.0181",
        "Resistencia_AC_25C_ohm_kft": "0.0191",
        "Resistencia_AC_75C_ohm_kft": "0.0234",
        "Ampacidad_75C_STD_ohm_kft": "970",
        "Ampacidad_75C_EX3": "1110",
        "Radio_Medio_Generico_ft": "0.0369",
        "Reactancia_Industrial_ohm_kft": "0.0758",
        "Reactancia_Capacitiva_Mohm_kft": "0.4773"
      }
    },
    "Phoenix": {
      "Tipo": "ACSR",
      "mecanicas": {
        "Tamaño_kcmil": "954.0",
        "Trenzado_Al": "42x0.1507",
        "Trenzado_Acero": "7x0.0837",
        "Seccion_Total_sqin": "0.7877",
        "Seccion_Al_sqin": "0.7491",
        "Diametro_Exterior_in": "1.155",
        "Peso_Total_lbs_kft": "1029",
        "Peso_Al_lbs_kft": "898.5",
        "Peso_Acero_lbs_kft": "130.5",
        "Porcentaje_Peso_Al_lbs_kft": "87.32%",
        "Porcentaje_Peso_Acero_lbs_kft": "12.88%",
        "Resistencia_GA2_lbs": "23400",
        "Resistencia_GA3_HS_lbs": "24100",
        "Resistencia_GA5_UHS_lbs": "24900"
      },
      "electricas": {
        "Tamaño_kcmil": "954.0",
        "Trenzado_Al": "42x0.1507",
        "Trenzado_Acero": "7x0.0837",
        "Seccion_Total_sqin": "0.7877",
        "Seccion_Al_sqin": "0.7491",
        "Diametro_Exterior_in": "1.155",
        "Resistencia_DC_20C_ohm_kft": "0.0181",
        "Resistencia_AC_25C_ohm_kft": "0.0190",
        "Resistencia_AC_75C_ohm_kft": "0.0233",
        "Ampacidad_75C_STD_ohm_kft": "975",
        "Ampacidad_75C_EX3": "1115",
        "Radio_Medio_Generico_ft": "0.0378",
        "Reactancia_Industrial_ohm_kft": "0.0753",
        "Reactancia_Capacitiva_Mohm_kft": "0.4752"
      }
    },
    "Corncrake": {
      "Tipo": "ACSR",
      "mecanicas": {
        "Tamaño_kcmil": "954.0",
        "Trenzado_Al": "20x0.2144",
        "Trenzado_Acero": "7x0.0971",
        "Seccion_Total_sqin": "0.8011",
        "Seccion_Al_sqin": "0.7482",
        "Diametro_Exterior_in": "1.165",
        "Peso_Total_lbs_kft": "1070",
        "Peso_Al_lbs_kft": "894.6",
        "Peso_Acero_lbs_kft": "175.6",
        "Porcentaje_Peso_Al_lbs_kft": "83.61%",
        "Porcentaje_Peso_Acero_lbs_kft": "16.41%",
        "Resistencia_GA2_lbs": "25600",
        "Resistencia_GA3_HS_lbs": "26600",
        "Resistencia_GA5_UHS_lbs": "27600"
      },
      "electricas": {
        "Tamaño_kcmil": "954.0",
        "Trenzado_Al": "20x0.2144",
        "Trenzado_Acero": "7x0.0971",
        "Seccion_Total_sqin": "0.8011",
        "Seccion_Al_sqin": "0.7482",
        "Diametro_Exterior_in": "1.165",
        "Resistencia_DC_20C_ohm_kft": "0.0179",
        "Resistencia_AC_25C_ohm_kft": "0.0187",
        "Resistencia_AC_75C_ohm_kft": "0.0223",
        "Ampacidad_75C_STD_ohm_kft": "1000",
        "Ampacidad_75C_EX3": "1150",
        "Radio_Medio_Generico_ft": "0.0380",
        "Reactancia_Industrial_ohm_kft": "0.0752",
        "Reactancia_Capacitiva_Mohm_kft": "0.4739"
      }
    },
    "Rail": {
      "Tipo": "ACSR",
      "mecanicas": {
        "Tamaño_kcmil": "954.0",
        "Trenzado_Al": "45x0.1456",
        "Trenzado_Acero": "7x0.0971",
        "Seccion_Total_sqin": "0.8011",
        "Seccion_Al_sqin": "0.7482",
        "Diametro_Exterior_in": "1.165",
        "Peso_Total_lbs_kft": "1075",
        "Peso_Al_lbs_kft": "895.0",
        "Peso_Acero_lbs_kft": "175.6",
        "Porcentaje_Peso_Al_lbs_kft": "83.63%",
        "Porcentaje_Peso_Acero_lbs_kft": "16.33%",
        "Resistencia_GA2_lbs": "25900",
        "Resistencia_GA3_HS_lbs": "26800",
        "Resistencia_GA5_UHS_lbs": "27900"
      },
      "electricas": {
        "Tamaño_kcmil": "954.0",
        "Trenzado_Al": "45x0.1456",
        "Trenzado_Acero": "7x0.0971",
        "Seccion_Total_sqin": "0.8011",
        "Seccion_Al_sqin": "0.7482",
        "Diametro_Exterior_in": "1.165",
        "Resistencia_DC_20C_ohm_kft": "0.0180",
        "Resistencia_AC_25C_ohm_kft": "0.0189",
        "Resistencia_AC_75C_ohm_kft": "0.0233",
        "Ampacidad_75C_STD_ohm_kft": "975",
        "Ampacidad_75C_EX3": "1120",
        "Radio_Medio_Generico_ft": "0.0384",
        "Reactancia_Industrial_ohm_kft": "0.0749",
        "Reactancia_Capacitiva_Mohm_kft": "0.4739"
      }
    },
    "Phoenix_ACSS": {
        "Tipo": "ACSS",
        "mecanicas": {
        "Tamaño_kcmil": "954.0",
        "Trenzado_Al": "42x0.1507",
        "Trenzado_Acero": "7x0.0837",
        "Seccion_Total_sqin": "0.7877",
        "Seccion_Al_sqin": "0.7491",
        "Diametro_Exterior_in": "1.155",
        "Peso_Total_lbs_kft": "1029",
        "Peso_Al_lbs_kft": "898.5",
        "Peso_Acero_lbs_kft": "130.5",
        "Porcentaje_Peso_Al_lbs_kft": "87.32%",
        "Porcentaje_Peso_Acero_lbs_kft": "12.68%",
        "Resistencia_MA2_lbs": "14200",
        "Resistencia_MA3_HS_lbs": "15200",
        "Resistencia_MA5_UHS_lbs": "17100"
        },
        "electricas": {
        "Tamaño_kcmil": "954.0",
        "Trenzado_Al": "42x0.1507",
        "Trenzado_Acero": "7x0.0837",
        "Seccion_Total_sqin": "0.7877",
        "Seccion_Al_sqin": "0.7491",
        "Diametro_Exterior_in": "1.155",
        "Resistencia_DC_20C_ohm_kft": "0.0176",
        "Resistencia_AC_25C_ohm_kft": "0.0185",
        "Resistencia_AC_75C_ohm_kft": "0.0228",
        "Resistencia_AC_200C": "0.0330",
        "Ampacidad_75C_STD_ohm_kft": "985",
        "Ampacidad_75C_EX3": "1130",
        "Ampacidad_200C_STD": "1770",
        "Ampacidad_200C_EX3": "2000",
        "Radio_Medio_Generico_ft": "0.0378",
        "Reactancia_Industrial_ohm_kft": "0.0753",
        "Reactancia_Capacitiva_Mohm_kft": "0.4752"
        }
    },
    "Corncrake_ACSS": {
        "Tipo": "ACSS",
        "mecanicas": {
        "Tamaño_kcmil": "954.0",
        "Trenzado_Al": "20x0.2184",
        "Trenzado_Acero": "7x0.0971",
        "Seccion_Total_sqin": "0.8011",
        "Seccion_Al_sqin": "0.7492",
        "Diametro_Exterior_in": "1.165",
        "Peso_Total_lbs_kft": "1070",
        "Peso_Al_lbs_kft": "894.6",
        "Peso_Acero_lbs_kft": "175.6",
        "Porcentaje_Peso_Al_lbs_kft": "83.61%",
        "Porcentaje_Peso_Acero_lbs_kft": "16.41%",
        "Resistencia_MA2_lbs": "16700",
        "Resistencia_MA3_HS_lbs": "18000",
        "Resistencia_MA5_UHS_lbs": "20400"
        },
        "electricas": {
        "Tamaño_kcmil": "954.0",
        "Trenzado_Al": "20x0.2184",
        "Trenzado_Acero": "7x0.0971",
        "Seccion_Total_sqin": "0.8011",
        "Seccion_Al_sqin": "0.7492",
        "Diametro_Exterior_in": "1.165",
        "Resistencia_DC_20C_ohm_kft": "0.0174",
        "Resistencia_AC_25C_ohm_kft": "0.0182",
        "Resistencia_AC_75C_ohm_kft": "0.0218",
        "Resistencia_AC_200C": "0.0307",
        "Ampacidad_75C_STD_ohm_kft": "1010",
        "Ampacidad_75C_EX3": "1160",
        "Ampacidad_200C_STD": "1840",
        "Ampacidad_200C_EX3": "2085",
        "Radio_Medio_Generico_ft": "0.0380",
        "Reactancia_Industrial_ohm_kft": "0.0752",
        "Reactancia_Capacitiva_Mohm_kft": "0.4739"
        }
    },
    "Rail_ACSS": {
        "Tipo": "ACSS",
        "mecanicas": {
        "Tamaño_kcmil": "954.0",
        "Trenzado_Al": "45x0.1456",
        "Trenzado_Acero": "7x0.0971",
        "Seccion_Total_sqin": "0.8011",
        "Seccion_Al_sqin": "0.7492",
        "Diametro_Exterior_in": "1.165",
        "Peso_Total_lbs_kft": "1075",
        "Peso_Al_lbs_kft": "899.0",
        "Peso_Acero_lbs_kft": "175.6",
        "Porcentaje_Peso_Al_lbs_kft": "83.63%",
        "Porcentaje_Peso_Acero_lbs_kft": "16.33%",
        "Resistencia_MA2_lbs": "16700",
        "Resistencia_MA3_HS_lbs": "18000",
        "Resistencia_MA5_UHS_lbs": "20400"
        },
        "electricas": {
        "Tamaño_kcmil": "954.0",
        "Trenzado_Al": "45x0.1456",
        "Trenzado_Acero": "7x0.0971",
        "Seccion_Total_sqin": "0.8011",
        "Seccion_Al_sqin": "0.7492",
        "Diametro_Exterior_in": "1.165",
        "Resistencia_DC_20C_ohm_kft": "0.0175",
        "Resistencia_AC_25C_ohm_kft": "0.0184",
        "Resistencia_AC_75C_ohm_kft": "0.0227",
        "Resistencia_AC_200C": "0.0329",
        "Ampacidad_75C_STD_ohm_kft": "990",
        "Ampacidad_75C_EX3": "1135",
        "Ampacidad_200C_STD": "1780",
        "Ampacidad_200C_EX3": "2010",
        "Radio_Medio_Generico_ft": "0.0384",
        "Reactancia_Industrial_ohm_kft": "0.0749",
        "Reactancia_Capacitiva_Mohm_kft": "0.4739"
         }
        }
    },
      "Drake": {
    "Tipo": "ACCC/TW",
    "mecanicas": {
      "Tamaño_kcmil": "1026",
      "No_Al_Wires": "18",
      "Composite_Core_OD_in": "0.375",
      "Seccion_Total_sqin": "0.9159",
      "Seccion_Al_sqin": "0.8055",
      "Diametro_Exterior_in": "1.11",
      "Peso_Total_lbs_kft": "1052",
      "Peso_Al_lbs_kft": "963",
      "Peso_Core_lbs_kft": "89",
      "Resistencia_Standard_lbs": "41100",
      "Resistencia_ULS_lbs": "48000"
    },
    "electricas": {
      "Tamaño_kcmil": "1026",
      "Diametro_Exterior_in": "1.11",
      "Resistencia_DC_20C_ohm_kft": "0.0164",
      "Resistencia_AC_25C_ohm_kft": "0.0171",
      "Resistencia_AC_75C_ohm_kft": "0.0205",
      "Ampacidad_75C_STD": "1030",
      "Ampacidad_75C_EX3": "1180",
      "Ampacidad_180C_STD": "1770",
      "Ampacidad_180C_EX3": "1995",
      "Radio_Medio_Generico_ft": "0.0375",
      "Reactancia_Industrial_ohm_kft": "0.0755",
      "Reactancia_Capacitiva_Mohm_kft": "0.4818"
    }
  },
  "Curlew": {
    "Tipo": "ACCC/TW",
    "mecanicas": {
      "Tamaño_kcmil": "1053",
      "No_Al_Wires": "20",
      "Composite_Core_OD_in": "0.415",
      "Seccion_Total_sqin": "0.9626",
      "Seccion_Al_sqin": "0.8273",
      "Diametro_Exterior_in": "1.14",
      "Peso_Total_lbs_kft": "1099",
      "Peso_Al_lbs_kft": "990",
      "Peso_Core_lbs_kft": "109",
      "Resistencia_Standard_lbs": "49100",
      "Resistencia_ULS_lbs": "57500"
    },
    "electricas": {
      "Tamaño_kcmil": "1053",
      "Diametro_Exterior_in": "1.14",
      "Resistencia_DC_20C_ohm_kft": "0.0160",
      "Resistencia_AC_25C_ohm_kft": "0.0167",
      "Resistencia_AC_75C_ohm_kft": "0.0199",
      "Ampacidad_75C_STD": "1050",
      "Ampacidad_75C_EX3": "1205",
      "Ampacidad_180C_STD": "1810",
      "Ampacidad_180C_EX3": "2040",
      "Radio_Medio_Generico_ft": "0.0387",
      "Reactancia_Industrial_ohm_kft": "0.0747",
      "Reactancia_Capacitiva_Mohm_kft": "0.4778"
    }
  },
  "Plano": {
    "Tipo": "ACCC/TW",
    "mecanicas": {
      "Tamaño_kcmil": "1059",
      "No_Al_Wires": "33",
      "Composite_Core_OD_in": "0.345",
      "Seccion_Total_sqin": "0.9258",
      "Seccion_Al_sqin": "0.8323",
      "Diametro_Exterior_in": "1.13",
      "Peso_Total_lbs_kft": "1074",
      "Peso_Al_lbs_kft": "999",
      "Peso_Core_lbs_kft": "75",
      "Resistencia_Standard_lbs": "36100",
      "Resistencia_ULS_lbs": "41800"
    },
    "electricas": {
      "Tamaño_kcmil": "1059",
      "Diametro_Exterior_in": "1.13",
      "Resistencia_DC_20C_ohm_kft": "0.0159",
      "Resistencia_AC_25C_ohm_kft": "0.0167",
      "Resistencia_AC_75C_ohm_kft": "0.0199",
      "Ampacidad_75C_STD": "1045",
      "Ampacidad_75C_EX3": "1200",
      "Ampacidad_180C_STD": "1805",
      "Ampacidad_180C_EX3": "2035",
      "Radio_Medio_Generico_ft": "0.0380",
      "Reactancia_Industrial_ohm_kft": "0.0752",
      "Reactancia_Capacitiva_Mohm_kft": "0.4790"
    }
  },
  "Corpus_Christi": {
    "Tipo": "ACCC/TW",
    "mecanicas": {
      "Tamaño_kcmil": "1103",
      "No_Al_Wires": "33",
      "Composite_Core_OD_in": "0.345",
      "Seccion_Total_sqin": "0.9596",
      "Seccion_Al_sqin": "0.8661",
      "Diametro_Exterior_in": "1.15",
      "Peso_Total_lbs_kft": "1115",
      "Peso_Al_lbs_kft": "1040",
      "Peso_Core_lbs_kft": "75",
      "Resistencia_Standard_lbs": "36300",
      "Resistencia_ULS_lbs": "42100"
    },
    "electricas": {
      "Tamaño_kcmil": "1103",
      "Diametro_Exterior_in": "1.15",
      "Resistencia_DC_20C_ohm_kft": "0.0153",
      "Resistencia_AC_25C_ohm_kft": "0.0161",
      "Resistencia_AC_75C_ohm_kft": "0.0192",
      "Ampacidad_75C_STD": "1070",
      "Ampacidad_75C_EX3": "1230",
      "Ampacidad_180C_STD": "1850",
      "Ampacidad_180C_EX3": "2090",
      "Radio_Medio_Generico_ft": "0.0386",
      "Reactancia_Industrial_ohm_kft": "0.0748",
      "Reactancia_Capacitiva_Mohm_kft": "0.4763"
    }
  },
    "Condor": {
    "Tipo": "ACSR",
    "mecanicas": {
      "Tamaño_kcmil": "795.0",
      "Trenzado_Al": "54x0.1213",
      "Trenzado_Acero": "7x0.1213",
      "Seccion_Total_sqin": "0.7049",
      "Seccion_Al_sqin": "0.6240",
      "Diametro_Exterior_in": "1.092",
      "Peso_Total_lbs_kft": "1024",
      "Peso_Al_lbs_kft": "748.8",
      "Peso_Acero_lbs_kft": "274.0",
      "Porcentaje_Peso_Al_lbs_kft": "73.22%",
      "Porcentaje_Peso_Acero_lbs_kft": "26.76%",
      "Resistencia_GA2_lbs": "28000",
      "Resistencia_GA3_HS_lbs": "29700",
      "Resistencia_GA5_UHS_lbs": "31300"
    },
    "electricas": {
      "Tamaño_kcmil": "795.0",
      "Trenzado_Al": "54x0.1213",
      "Trenzado_Acero": "7x0.1213",
      "Seccion_Total_sqin": "0.7049",
      "Seccion_Al_sqin": "0.6240",
      "Diametro_Exterior_in": "1.092",
      "Resistencia_DC_20C_ohm_kft": "0.0215",
      "Resistencia_AC_25C_ohm_kft": "0.0224",
      "Resistencia_AC_75C_ohm_kft": "0.0276",
      "Ampacidad_75C_STD_ohm_kft": "880",
      "Ampacidad_75C_EX3": "1010",
      "Radio_Medio_Generico_ft": "0.0366",
      "Reactancia_Industrial_ohm_kft": "0.0760",
      "Reactancia_Capacitiva_Mohm_kft": "0.4841"
    }
  },
  "Drake_ACSR": {
    "Tipo": "ACSR",
    "mecanicas": {
      "Tamaño_kcmil": "795.0",
      "Trenzado_Al": "26x0.1749",
      "Trenzado_Acero": "7x0.1360",
      "Seccion_Total_sqin": "0.7263",
      "Seccion_Al_sqin": "0.6247",
      "Diametro_Exterior_in": "1.108",
      "Peso_Total_lbs_kft": "1091",
      "Peso_Al_lbs_kft": "746.8",
      "Peso_Acero_lbs_kft": "344.4",
      "Porcentaje_Peso_Al_lbs_kft": "68.45%",
      "Porcentaje_Peso_Acero_lbs_kft": "31.57%",
      "Resistencia_GA2_lbs": "31500",
      "Resistencia_GA3_HS_lbs": "33500",
      "Resistencia_GA5_UHS_lbs": "35400"
    },
    "electricas": {
      "Tamaño_kcmil": "795.0",
      "Trenzado_Al": "26x0.1749",
      "Trenzado_Acero": "7x0.1360",
      "Seccion_Total_sqin": "0.7263",
      "Seccion_Al_sqin": "0.6247",
      "Diametro_Exterior_in": "1.108",
      "Resistencia_DC_20C_ohm_kft": "0.0213",
      "Resistencia_AC_25C_ohm_kft": "0.0219",
      "Resistencia_AC_75C_ohm_kft": "0.0262",
      "Ampacidad_75C_STD_ohm_kft": "910",
      "Ampacidad_75C_EX3": "1040",
      "Radio_Medio_Generico_ft": "0.0372",
      "Reactancia_Industrial_ohm_kft": "0.0756",
      "Reactancia_Capacitiva_Mohm_kft": "0.4818"
    }
  },
  "Mallard": {
    "Tipo": "ACSR",
    "mecanicas": {
      "Tamaño_kcmil": "795.0",
      "Trenzado_Al": "30x0.1628",
      "Trenzado_Acero": "19x0.0977",
      "Seccion_Total_sqin": "0.7669",
      "Seccion_Al_sqin": "0.6245",
      "Diametro_Exterior_in": "1.140",
      "Peso_Total_lbs_kft": "1232",
      "Peso_Al_lbs_kft": "747.6",
      "Peso_Acero_lbs_kft": "484.4",
      "Porcentaje_Peso_Al_lbs_kft": "60.88%",
      "Porcentaje_Peso_Acero_lbs_kft": "39.32%",
      "Resistencia_GA2_lbs": "38400",
      "Resistencia_GA3_HS_lbs": "41100",
      "Resistencia_GA5_UHS_lbs": "43700"
    },
    "electricas": {
      "Tamaño_kcmil": "795.0",
      "Trenzado_Al": "30x0.1628",
      "Trenzado_Acero": "19x0.0977",
      "Seccion_Total_sqin": "0.7669",
      "Seccion_Al_sqin": "0.6245",
      "Diametro_Exterior_in": "1.140",
      "Resistencia_DC_20C_ohm_kft": "0.0211",
      "Resistencia_AC_25C_ohm_kft": "0.0217",
      "Resistencia_AC_75C_ohm_kft": "0.0259",
      "Ampacidad_75C_STD_ohm_kft": "920",
      "Ampacidad_75C_EX3": "1055",
      "Radio_Medio_Generico_ft": "0.0389",
      "Reactancia_Industrial_ohm_kft": "0.0746",
      "Reactancia_Capacitiva_Mohm_kft": "0.4773"
    }
  },
    "Condor_TW": {
    "Tipo": "ACSR/TW",
    "mecanicas": {
      "Tamaño_kcmil": "795.0",
      "Tipo_num": "13",
      "No_Al_Wires": "18",
      "Fill_Factor": "93.3",
      "Equiv_Al_Dia_in": "0.2102",
      "Trenzado_Acero": "7x0.1213",
      "Steel_Core_OD_in": "0.364",
      "Seccion_Total_sqin": "0.7055",
      "Seccion_Al_sqin": "0.6246",
      "Diametro_Exterior_in": "0.991",
      "Peso_Total_lbs_kft": "1021",
      "Peso_Al_lbs_kft": "747.0",
      "Peso_Acero_lbs_kft": "274.0",
      "Porcentaje_Peso_Al_lbs_kft": "73.16%",
      "Porcentaje_Peso_Acero_lbs_kft": "26.84%",
      "Resistencia_GA2_lbs": "27900",
      "Resistencia_GA3_HS_lbs": "29500",
      "Resistencia_GA5_UHS_lbs": "31000"
    },
    "electricas": {
      "Tamaño_kcmil": "795.0",
      "Tipo_num": "13",
      "No_Al_Wires": "18",
      "Fill_Factor": "93.3",
      "Equiv_Al_Dia_in": "0.2102",
      "Trenzado_Acero": "7x0.1213",
      "Steel_Core_OD_in": "0.364",
      "Seccion_Total_sqin": "0.7055",
      "Seccion_Al_sqin": "0.6246",
      "Diametro_Exterior_in": "0.991",
      "Resistencia_DC_20C_ohm_kft": "0.0214",
      "Resistencia_AC_25C_ohm_kft": "0.0221",
      "Resistencia_AC_75C_ohm_kft": "0.0263",
      "Ampacidad_75C_STD_ohm_kft": "880",
      "Ampacidad_75C_EX3": "1005",
      "Radio_Medio_Generico_ft": "0.0336",
      "Reactancia_Industrial_ohm_kft": "0.0780",
      "Reactancia_Capacitiva_Mohm_kft": "0.4992"
    }
  },
  "Drake_ACSR_TW": {
    "Tipo": "ACSR/TW",
    "mecanicas": {
      "Tamaño_kcmil": "795.0",
      "Tipo_num": "16",
      "No_Al_Wires": "20",
      "Fill_Factor": "92.8",
      "Equiv_Al_Dia_in": "0.1994",
      "Trenzado_Acero": "7x0.1360",
      "Steel_Core_OD_in": "0.408",
      "Seccion_Total_sqin": "0.7262",
      "Seccion_Al_sqin": "0.6246",
      "Diametro_Exterior_in": "1.010",
      "Peso_Total_lbs_kft": "1092",
      "Peso_Al_lbs_kft": "747.3",
      "Peso_Acero_lbs_kft": "344.4",
      "Porcentaje_Peso_Al_lbs_kft": "68.43%",
      "Porcentaje_Peso_Acero_lbs_kft": "31.54%",
      "Resistencia_GA2_lbs": "31800",
      "Resistencia_GA3_HS_lbs": "33800",
      "Resistencia_GA5_UHS_lbs": "35700"
    },
    "electricas": {
      "Tamaño_kcmil": "795.0",
      "Tipo_num": "16",
      "No_Al_Wires": "20",
      "Fill_Factor": "92.8",
      "Equiv_Al_Dia_in": "0.1994",
      "Trenzado_Acero": "7x0.1360",
      "Steel_Core_OD_in": "0.408",
      "Seccion_Total_sqin": "0.7262",
      "Seccion_Al_sqin": "0.6246",
      "Diametro_Exterior_in": "1.010",
      "Resistencia_DC_20C_ohm_kft": "0.0213",
      "Resistencia_AC_25C_ohm_kft": "0.0219",
      "Resistencia_AC_75C_ohm_kft": "0.0262",
      "Ampacidad_75C_STD_ohm_kft": "885",
      "Ampacidad_75C_EX3": "1010",
      "Radio_Medio_Generico_ft": "0.0346",
      "Reactancia_Industrial_ohm_kft": "0.0773",
      "Reactancia_Capacitiva_Mohm_kft": "0.4962"
    }
  },
  "Mallard_TW": {
    "Tipo": "ACSR/TW",
    "mecanicas": {
      "Tamaño_kcmil": "795.0",
      "Tipo_num": "23",
      "No_Al_Wires": "22",
      "Fill_Factor": "92.4",
      "Equiv_Al_Dia_in": "0.1901",
      "Trenzado_Acero": "19x0.0977",
      "Steel_Core_OD_in": "0.488",
      "Seccion_Total_sqin": "0.7669",
      "Seccion_Al_sqin": "0.6244",
      "Diametro_Exterior_in": "1.047",
      "Peso_Total_lbs_kft": "1232",
      "Peso_Al_lbs_kft": "747.9",
      "Peso_Acero_lbs_kft": "484.4",
      "Porcentaje_Peso_Al_lbs_kft": "60.71%",
      "Porcentaje_Peso_Acero_lbs_kft": "39.32%",
      "Resistencia_GA2_lbs": "38700",
      "Resistencia_GA3_HS_lbs": "41400",
      "Resistencia_GA5_UHS_lbs": "44000"
    },
    "electricas": {
      "Tamaño_kcmil": "795.0",
      "Tipo_num": "23",
      "No_Al_Wires": "22",
      "Fill_Factor": "92.4",
      "Equiv_Al_Dia_in": "0.1901",
      "Trenzado_Acero": "19x0.0977",
      "Steel_Core_OD_in": "0.488",
      "Seccion_Total_sqin": "0.7669",
      "Seccion_Al_sqin": "0.6244",
      "Diametro_Exterior_in": "1.047",
      "Resistencia_DC_20C_ohm_kft": "0.0211",
      "Resistencia_AC_25C_ohm_kft": "0.0217",
      "Resistencia_AC_75C_ohm_kft": "0.0259",
      "Ampacidad_75C_STD_ohm_kft": "900",
      "Ampacidad_75C_EX3": "1030",
      "Radio_Medio_Generico_ft": "0.0364",
      "Reactancia_Industrial_ohm_kft": "0.0761",
      "Reactancia_Capacitiva_Mohm_kft": "0.4906"
    }
  },
    "Condor_ACSS": {
    "Tipo": "ACSS",
    "mecanicas": {
      "Tamaño_kcmil": "795.0",
      "Trenzado_Al": "54x0.1213",
      "Trenzado_Acero": "7x0.1213",
      "Seccion_Total_sqin": "0.7049",
      "Seccion_Al_sqin": "0.6240",
      "Diametro_Exterior_in": "1.092",
      "Peso_Total_lbs_kft": "1024",
      "Peso_Al_lbs_kft": "749.8",
      "Peso_Acero_lbs_kft": "274.0",
      "Porcentaje_Peso_Al_lbs_kft": "73.22%",
      "Porcentaje_Peso_Acero_lbs_kft": "26.76%",
      "Resistencia_MA2_lbs": "21700",
      "Resistencia_MA3_HS_lbs": "23300",
      "Resistencia_MA5_UHS_lbs": "26900"
    },
    "electricas": {
      "Tamaño_kcmil": "795.0",
      "Trenzado_Al": "54x0.1213",
      "Trenzado_Acero": "7x0.1213",
      "Seccion_Total_sqin": "0.7049",
      "Seccion_Al_sqin": "0.6240",
      "Diametro_Exterior_in": "1.092",
      "Resistencia_DC_20C_ohm_kft": "0.0209",
      "Resistencia_AC_25C_ohm_kft": "0.0218",
      "Resistencia_AC_75C_ohm_kft": "0.0270",
      "Resistencia_AC_200C": "0.0392",
      "Ampacidad_75C_STD_ohm_kft": "890",
      "Ampacidad_75C_EX3": "1020",
      "Ampacidad_200C_STD": "1595",
      "Ampacidad_200C_EX3": "1800",
      "Radio_Medio_Generico_ft": "0.0366",
      "Reactancia_Industrial_ohm_kft": "0.0760",
      "Reactancia_Capacitiva_Mohm_kft": "0.4841"
    }
  },
  "Drake_ACSS": {
    "Tipo": "ACSS",
    "mecanicas": {
      "Tamaño_kcmil": "795.0",
      "Trenzado_Al": "26x0.1749",
      "Trenzado_Acero": "7x0.1360",
      "Seccion_Total_sqin": "0.7263",
      "Seccion_Al_sqin": "0.6247",
      "Diametro_Exterior_in": "1.108",
      "Peso_Total_lbs_kft": "1091",
      "Peso_Al_lbs_kft": "746.8",
      "Peso_Acero_lbs_kft": "344.4",
      "Porcentaje_Peso_Al_lbs_kft": "68.45%",
      "Porcentaje_Peso_Acero_lbs_kft": "31.57%",
      "Resistencia_MA2_lbs": "25900",
      "Resistencia_MA3_HS_lbs": "28000",
      "Resistencia_MA5_UHS_lbs": "32600"
    },
    "electricas": {
      "Tamaño_kcmil": "795.0",
      "Trenzado_Al": "26x0.1749",
      "Trenzado_Acero": "7x0.1360",
      "Seccion_Total_sqin": "0.7263",
      "Seccion_Al_sqin": "0.6247",
      "Diametro_Exterior_in": "1.108",
      "Resistencia_DC_20C_ohm_kft": "0.0207",
      "Resistencia_AC_25C_ohm_kft": "0.0214",
      "Resistencia_AC_75C_ohm_kft": "0.0256",
      "Resistencia_AC_200C": "0.0382",
      "Ampacidad_75C_STD_ohm_kft": "920",
      "Ampacidad_75C_EX3": "1055",
      "Ampacidad_200C_STD": "1665",
      "Ampacidad_200C_EX3": "1890",
      "Radio_Medio_Generico_ft": "0.0372",
      "Reactancia_Industrial_ohm_kft": "0.0756",
      "Reactancia_Capacitiva_Mohm_kft": "0.4818"
    }
  },
  "Mallard_ACSS": {
    "Tipo": "ACSS",
    "mecanicas": {
      "Tamaño_kcmil": "795.0",
      "Trenzado_Al": "30x0.1628",
      "Trenzado_Acero": "19x0.0977",
      "Seccion_Total_sqin": "0.7669",
      "Seccion_Al_sqin": "0.6245",
      "Diametro_Exterior_in": "1.140",
      "Peso_Total_lbs_kft": "1232",
      "Peso_Al_lbs_kft": "747.6",
      "Peso_Acero_lbs_kft": "484.4",
      "Porcentaje_Peso_Al_lbs_kft": "60.68%",
      "Porcentaje_Peso_Acero_lbs_kft": "39.32%",
      "Resistencia_MA2_lbs": "34300",
      "Resistencia_MA3_HS_lbs": "37900",
      "Resistencia_MA5_UHS_lbs": "44300"
    },
    "electricas": {
      "Tamaño_kcmil": "795.0",
      "Trenzado_Al": "30x0.1628",
      "Trenzado_Acero": "19x0.0977",
      "Seccion_Total_sqin": "0.7669",
      "Seccion_Al_sqin": "0.6245",
      "Diametro_Exterior_in": "1.140",
      "Resistencia_DC_20C_ohm_kft": "0.0205",
      "Resistencia_AC_25C_ohm_kft": "0.0212",
      "Resistencia_AC_75C_ohm_kft": "0.0253",
      "Resistencia_AC_200C": "0.0359",
      "Ampacidad_75C_STD_ohm_kft": "930",
      "Ampacidad_75C_EX3": "1070",
      "Ampacidad_200C_STD": "1690",
      "Ampacidad_200C_EX3": "1915",
      "Radio_Medio_Generico_ft": "0.0389",
      "Reactancia_Industrial_ohm_kft": "0.0746",
      "Reactancia_Capacitiva_Mohm_kft": "0.4773"
    }
  },
    "Condor_ACSS_TW": {
    "Tipo": "ACSS/TW",
    "mecanicas": {
      "Tamaño_kcmil": "795.0",
      "Tipo_num": "13",
      "No_Al_Wires": "18",
      "Fill_Factor": "93.3",
      "Equiv_Al_Dia_in": "0.2102",
      "Trenzado_Acero": "7x0.1213",
      "Steel_Core_OD_in": "0.364",
      "Seccion_Total_sqin": "0.7055",
      "Seccion_Al_sqin": "0.6246",
      "Diametro_Exterior_in": "0.991",
      "Peso_Total_lbs_kft": "1021",
      "Peso_Al_lbs_kft": "747.0",
      "Peso_Acero_lbs_kft": "274.0",
      "Porcentaje_Peso_Al_lbs_kft": "73.16%",
      "Porcentaje_Peso_Acero_lbs_kft": "26.84%",
      "Resistencia_MA2_lbs": "21700",
      "Resistencia_MA3_HS_lbs": "23300",
      "Resistencia_MA5_UHS_lbs": "26900"
    },
    "electricas": {
      "Tamaño_kcmil": "795.0",
      "Tipo_num": "13",
      "No_Al_Wires": "18",
      "Fill_Factor": "93.3",
      "Equiv_Al_Dia_in": "0.2102",
      "Trenzado_Acero": "7x0.1213",
      "Steel_Core_OD_in": "0.364",
      "Seccion_Total_sqin": "0.7055",
      "Seccion_Al_sqin": "0.6246",
      "Diametro_Exterior_in": "0.991",
      "Resistencia_DC_20C_ohm_kft": "0.0208",
      "Resistencia_AC_25C_ohm_kft": "0.0215",
      "Resistencia_AC_75C_ohm_kft": "0.0257",
      "Resistencia_AC_200C": "0.0364",
      "Ampacidad_75C_STD_ohm_kft": "890",
      "Ampacidad_75C_EX3": "1015",
      "Ampacidad_200C_STD": "1605",
      "Ampacidad_200C_EX3": "1810",
      "Radio_Medio_Generico_ft": "0.0336",
      "Reactancia_Industrial_ohm_kft": "0.0780",
      "Reactancia_Capacitiva_Mohm_kft": "0.4992"
    }
  },
  "Drake_ACSS_TW": {
    "Tipo": "ACSS/TW",
    "mecanicas": {
      "Tamaño_kcmil": "795.0",
      "Tipo_num": "16",
      "No_Al_Wires": "20",
      "Fill_Factor": "92.8",
      "Equiv_Al_Dia_in": "0.1994",
      "Trenzado_Acero": "7x0.1360",
      "Steel_Core_OD_in": "0.408",
      "Seccion_Total_sqin": "0.7262",
      "Seccion_Al_sqin": "0.6246",
      "Diametro_Exterior_in": "1.010",
      "Peso_Total_lbs_kft": "1092",
      "Peso_Al_lbs_kft": "747.3",
      "Peso_Acero_lbs_kft": "344.4",
      "Porcentaje_Peso_Al_lbs_kft": "68.43%",
      "Porcentaje_Peso_Acero_lbs_kft": "31.54%",
      "Resistencia_MA2_lbs": "25900",
      "Resistencia_MA3_HS_lbs": "28000",
      "Resistencia_MA5_UHS_lbs": "32600"
    },
    "electricas": {
      "Tamaño_kcmil": "795.0",
      "Tipo_num": "16",
      "No_Al_Wires": "20",
      "Fill_Factor": "92.8",
      "Equiv_Al_Dia_in": "0.1994",
      "Trenzado_Acero": "7x0.1360",
      "Steel_Core_OD_in": "0.408",
      "Seccion_Total_sqin": "0.7262",
      "Seccion_Al_sqin": "0.6246",
      "Diametro_Exterior_in": "1.010",
      "Resistencia_DC_20C_ohm_kft": "0.0207",
      "Resistencia_AC_25C_ohm_kft": "0.0214",
      "Resistencia_AC_75C_ohm_kft": "0.0256",
      "Resistencia_AC_200C": "0.0362",
      "Ampacidad_75C_STD_ohm_kft": "895",
      "Ampacidad_75C_EX3": "1025",
      "Ampacidad_200C_STD": "1620",
      "Ampacidad_200C_EX3": "1825",
      "Radio_Medio_Generico_ft": "0.0346",
      "Reactancia_Industrial_ohm_kft": "0.0773",
      "Reactancia_Capacitiva_Mohm_kft": "0.4962"
    }
  },
  "Mallard_ACSS_TW": {
    "Tipo": "ACSS/TW",
    "mecanicas": {
      "Tamaño_kcmil": "795.0",
      "Tipo_num": "23",
      "No_Al_Wires": "22",
      "Fill_Factor": "92.4",
      "Equiv_Al_Dia_in": "0.1901",
      "Trenzado_Acero": "19x0.0977",
      "Steel_Core_OD_in": "0.488",
      "Seccion_Total_sqin": "0.7669",
      "Seccion_Al_sqin": "0.6244",
      "Diametro_Exterior_in": "1.047",
      "Peso_Total_lbs_kft": "1232",
      "Peso_Al_lbs_kft": "747.9",
      "Peso_Acero_lbs_kft": "484.4",
      "Porcentaje_Peso_Al_lbs_kft": "60.71%",
      "Porcentaje_Peso_Acero_lbs_kft": "39.32%",
      "Resistencia_MA2_lbs": "34300",
      "Resistencia_MA3_HS_lbs": "37900",
      "Resistencia_MA5_UHS_lbs": "44300"
    },
    "electricas": {
      "Tamaño_kcmil": "795.0",
      "Tipo_num": "23",
      "No_Al_Wires": "22",
      "Fill_Factor": "92.4",
      "Equiv_Al_Dia_in": "0.1901",
      "Trenzado_Acero": "19x0.0977",
      "Steel_Core_OD_in": "0.488",
      "Seccion_Total_sqin": "0.7669",
      "Seccion_Al_sqin": "0.6244",
      "Diametro_Exterior_in": "1.047",
      "Resistencia_DC_20C_ohm_kft": "0.0205",
      "Resistencia_AC_25C_ohm_kft": "0.0211",
      "Resistencia_AC_75C_ohm_kft": "0.0253",
      "Resistencia_AC_200C": "0.0359",
      "Ampacidad_75C_STD_ohm_kft": "910",
      "Ampacidad_75C_EX3": "1040",
      "Ampacidad_200C_STD": "1645",
      "Ampacidad_200C_EX3": "1860",
      "Radio_Medio_Generico_ft": "0.0365",
      "Reactancia_Industrial_ohm_kft": "0.0761",
      "Reactancia_Capacitiva_Mohm_kft": "0.4906"
    }
  },
    "Lubbock": {
    "Tipo": "ACCC/TW",
    "mecanicas": {
      "Tamaño_kcmil": "904",
      "Equivalente_ACSR_kcmil": "",
      "No_Al_Wires": "18",
      "Composite_Core_OD_in": "0.345",
      "Seccion_Total_sqin": "0.8035",
      "Seccion_Al_sqin": "0.7100",
      "Diametro_Exterior_in": "1.04",
      "Peso_Total_lbs_kft": "924",
      "Peso_Al_lbs_kft": "849",
      "Peso_Core_lbs_kft": "75",
      "Resistencia_Standard_lbs": "35100",
      "Resistencia_ULS_lbs": "40800"
    },
    "electricas": {
      "Tamaño_kcmil": "904",
      "Diametro_Exterior_in": "1.04",
      "Resistencia_DC_20C_ohm_kft": "0.0186",
      "Resistencia_AC_25C_ohm_kft": "0.0193",
      "Resistencia_AC_75C_ohm_kft": "0.0231",
      "Ampacidad_75C_STD": "950",
      "Ampacidad_75C_EX3": "1085",
      "Ampacidad_180C_STD": "1630",
      "Ampacidad_180C_EX3": "1835",
      "Radio_Medio_Generico_ft": "0.0351",
      "Reactancia_Industrial_ohm_kft": "0.0770",
      "Reactancia_Capacitiva_Mohm_kft": "0.4917"
    }
  },
  "Galveston": {
    "Tipo": "ACCC/TW",
    "mecanicas": {
      "Tamaño_kcmil": "1011",
      "Equivalente_ACSR_kcmil": "",
      "No_Al_Wires": "18",
      "Composite_Core_OD_in": "0.345",
      "Seccion_Total_sqin": "0.8876",
      "Seccion_Al_sqin": "0.7941",
      "Diametro_Exterior_in": "1.09",
      "Peso_Total_lbs_kft": "1024",
      "Peso_Al_lbs_kft": "949",
      "Peso_Core_lbs_kft": "75",
      "Resistencia_Standard_lbs": "35700",
      "Resistencia_ULS_lbs": "41500"
    },
    "electricas": {
      "Tamaño_kcmil": "1011",
      "Diametro_Exterior_in": "1.09",
      "Resistencia_DC_20C_ohm_kft": "0.0166",
      "Resistencia_AC_25C_ohm_kft": "0.0174",
      "Resistencia_AC_75C_ohm_kft": "0.0208",
      "Ampacidad_75C_STD": "1015",
      "Ampacidad_75C_EX3": "1165",
      "Ampacidad_180C_STD": "1750",
      "Ampacidad_180C_EX3": "1970",
      "Radio_Medio_Generico_ft": "0.0367",
      "Reactancia_Industrial_ohm_kft": "0.0760",
      "Reactancia_Capacitiva_Mohm_kft": "0.4841"
    }
  }
}