{
  "Ac 70": {
    "tipo": "ACERO",
    "material": "Ac",
    "seccion_nominal": "70",
    "seccion_total_mm2": 72.23,
    "diametro_total_mm": 11.0,
    "peso_unitario_dan_m": 0.6,
    "coeficiente_dilatacion_1_c": 1.1e-05,
    "modulo_elasticidad_dan_mm2": 20000.0,
    "carga_rotura_minima_dan": 7000.0,
    "tension_rotura_minima": 96.91,
    "carga_max_trabajo": 1549.0,
    "tension_max_trabajo": 21.45,
    "norma_fabricacion": "IRAM 722"
  },
  "ADSS 1": {
    "tipo": "ADSS",
    "material": "Sintético",
    "seccion_nominal": null,
    "seccion_total_mm2": 5.3,
    "diametro_total_mm": 15.0,
    "peso_unitario_dan_m": 0.185,
    "coeficiente_dilatacion_1_c": 2e-06,
    "modulo_elasticidad_dan_mm2": 2191.6,
    "carga_rotura_minima_dan": 2242.6,
    "tension_rotura_minima": 423.1,
    "carga_max_trabajo": 2038.7,
    "tension_max_trabajo": null,
    "norma_fabricacion": null
  },
  "AlAc 435/55": {
    "tipo": "ACSR",
    "material": "Al/Ac",
    "seccion_nominal": "435/55",
    "seccion_total_mm2": 490.6,
    "diametro_total_mm": 28.8,
    "peso_unitario_dan_m": 1.653,
    "coeficiente_dilatacion_1_c": 1.93e-05,
    "modulo_elasticidad_dan_mm2": 7000.0,
    "carga_rotura_minima_dan": 13645.0,
    "tension_rotura_minima": 27.81,
    "carga_max_trabajo": 3650.0,
    "tension_max_trabajo": 7.44,
    "norma_fabricacion": "DIN 48204"
  },
  "AlAc 300/50": {
    "tipo": "ACSR",
    "material": "Al/Ac",
    "seccion_nominal": "300/50",
    "seccion_total_mm2": 353.7,
    "diametro_total_mm": 24.5,
    "peso_unitario_dan_m": 1.20663,
    "coeficiente_dilatacion_1_c": 1.89e-05,
    "modulo_elasticidad_dan_mm2": 7700.0,
    "carga_rotura_minima_dan": 10496.7,
    "tension_rotura_minima": 29.68,
    "carga_max_trabajo": 10496.7,
    "tension_max_trabajo": 20.776,
    "norma_fabricacion": "IRAM 2187"
  },
  "Ac 50": {
    "tipo": "ACERO",
    "material": "Ac",
    "seccion_nominal": "50",
    "seccion_total_mm2": 49.49,
    "diametro_total_mm": 9.0,
    "peso_unitario_dan_m": 0.3924,
    "coeficiente_dilatacion_1_c": 1.1e-05,
    "modulo_elasticidad_dan_mm2": 20000.0,
    "carga_rotura_minima_dan": 6674.0,
    "tension_rotura_minima": 134.9,
    "carga_max_trabajo": null,
    "tension_max_trabajo": null,
    "norma_fabricacion": "ASTM 363"
  },
  "Al/Ac 70/12": {
    "tipo": "ACSR",
    "material": "Al/Ac",
    "seccion_nominal": "70/12",
    "seccion_total_mm2": 81.3,
    "diametro_total_mm": 11.7,
    "peso_unitario_dan_m": 0.28746,
    "coeficiente_dilatacion_1_c": 1.89e-05,
    "modulo_elasticidad_dan_mm2": 7700.0,
    "carga_rotura_minima_dan": 2630.1,
    "tension_rotura_minima": 32.4,
    "carga_max_trabajo": 828.447,
    "tension_max_trabajo": 10.19,
    "norma_fabricacion": "IRAM 2187"
  },
  "OPGW 07A378s 12FO 62mm2": {
    "tipo": "OPGW",
    "material": "ACS",
    "seccion_nominal": null,
    "seccion_total_mm2": 62.4,
    "diametro_total_mm": 10.7,
    "peso_unitario_dan_m": 0.359,
    "coeficiente_dilatacion_1_c": 1.42e-05,
    "modulo_elasticidad_dan_mm2": 12458.7,
    "carga_rotura_minima_dan": 5542.7,
    "tension_rotura_minima": 88.8,
    "carga_max_trabajo": null,
    "tension_max_trabajo": null,
    "norma_fabricacion": "IEC/EN 60794"
  },
  "OPGW 44F70s 24FO 120mm2": {
    "tipo": "OPGW",
    "material": "ACS/A",
    "seccion_nominal": "120",
    "seccion_total_mm2": 120.0,
    "diametro_total_mm": 14.4,
    "peso_unitario_dan_m": 0.68642,
    "coeficiente_dilatacion_1_c": 1.4e-05,
    "modulo_elasticidad_dan_mm2": 12845.86,
    "carga_rotura_minima_dan": 11090.6,
    "tension_rotura_minima": 92.4,
    "carga_max_trabajo": 4436.2,
    "tension_max_trabajo": 37.0,
    "norma_fabricacion": "IEC/EN 60794"
  },
  "OPGW FiberHome 24FO 58mm2": {
    "tipo": "OPGW",
    "material": "ACS/A",
    "seccion_nominal": "58",
    "seccion_total_mm2": 57.73,
    "diametro_total_mm": 10.5,
    "peso_unitario_dan_m": 0.28927,
    "coeficiente_dilatacion_1_c": 1.55e-05,
    "modulo_elasticidad_dan_mm2": 10900.0,
    "carga_rotura_minima_dan": 3530.0,
    "tension_rotura_minima": 61.146,
    "carga_max_trabajo": 2471,
    "tension_max_trabajo": 42.825,
    "norma_fabricacion": "IEC/EN 60794"
  },
  "Ruddy": {
    "tipo": "ACSR",
    "material": "Al/Ac",
    "seccion_nominal": "900.0",
    "seccion_total_mm2": 487.42,
    "diametro_total_mm": 28.73,
    "peso_unitario_dan_m": 1.5073,
    "coeficiente_dilatacion_1_c": 2.2255658504301786e-05,
    "modulo_elasticidad_dan_mm2": 7747.9,
    "carga_rotura_minima_dan": 10853.1,
    "tension_rotura_minima": 22.27,
    "carga_max_trabajo": 2713.3,
    "tension_max_trabajo": 5.57,
    "norma_fabricacion": "ASTM B232",
    "datos_originales": {
      "tipo_original": "ACSR",
      "mecanicas": {
        "tamano_kcmil": 900.0,
        "trenzado_al": "45x0.1414",
        "trenzado_acero": "7x0.0943",
        "seccion_total_sqin": 0.7555,
        "seccion_al_sqin": 0.7066,
        "diametro_exterior_in": 1.131,
        "peso_total_lbs_kft": 1013.0,
        "peso_al_lbs_kft": 847.9,
        "peso_acero_lbs_kft": 165.6,
        "porcentaje_peso_al": 83.7,
        "porcentaje_peso_acero": 16.35,
        "resistencia_ga2_lbs": 24400.0
      },
      "electricas": {
        "resistencia_dc_20c_ohm_kft": 0.0191,
        "resistencia_ac_25c_ohm_kft": 0.02,
        "resistencia_ac_75c_ohm_kft": 0.0246,
        "ampacidad_75c_std": 940.0,
        "ampacidad_75c_ex3": 1080.0,
        "radio_medio_generico_ft": 0.0373,
        "reactancia_industrial_ohm_kft": 0.0756,
        "reactancia_capacitiva_mohm_kft": 0.4755
      }
    }
  },
  "Canary": {
    "tipo": "ACSR",
    "material": "Al/Ac",
    "seccion_nominal": "900.0",
    "seccion_total_mm2": 515.16,
    "diametro_total_mm": 29.51,
    "peso_unitario_dan_m": 1.7261,
    "coeficiente_dilatacion_1_c": 2.1709580463368816e-05,
    "modulo_elasticidad_dan_mm2": 8370.0,
    "carga_rotura_minima_dan": 14189.1,
    "tension_rotura_minima": 27.54,
    "carga_max_trabajo": 3547.3,
    "tension_max_trabajo": 6.89,
    "norma_fabricacion": "ASTM B232",
    "datos_originales": {
      "tipo_original": "ACSR",
      "mecanicas": {
        "tamano_kcmil": 900.0,
        "trenzado_al": "54x0.1291",
        "trenzado_acero": "7x0.1291",
        "seccion_total_sqin": 0.7985,
        "seccion_al_sqin": 0.7089,
        "diametro_exterior_in": 1.162,
        "peso_total_lbs_kft": 1160.0,
        "peso_al_lbs_kft": 849.4,
        "peso_acero_lbs_kft": 310.4,
        "porcentaje_peso_al": 73.22,
        "porcentaje_peso_acero": 26.76,
        "resistencia_ga2_lbs": 31900.0
      },
      "electricas": {
        "resistencia_dc_20c_ohm_kft": 0.019,
        "resistencia_ac_25c_ohm_kft": 0.0198,
        "resistencia_ac_75c_ohm_kft": 0.0244,
        "ampacidad_75c_std": 955.0,
        "ampacidad_75c_ex3": 1095.0,
        "radio_medio_generico_ft": 0.039,
        "reactancia_industrial_ohm_kft": 0.0746,
        "reactancia_capacitiva_mohm_kft": 0.4743
      }
    }
  },
  "Catbird": {
    "tipo": "ACSR",
    "material": "Al/Ac",
    "seccion_nominal": "954.0",
    "seccion_total_mm2": 496.9,
    "diametro_total_mm": 28.96,
    "peso_unitario_dan_m": 1.4672,
    "coeficiente_dilatacion_1_c": 2.2689431316541157e-05,
    "modulo_elasticidad_dan_mm2": 7253.8,
    "carga_rotura_minima_dan": 8807.0,
    "tension_rotura_minima": 17.72,
    "carga_max_trabajo": 2201.8,
    "tension_max_trabajo": 4.43,
    "norma_fabricacion": "ASTM B232",
    "datos_originales": {
      "tipo_original": "ACSR",
      "mecanicas": {
        "tamano_kcmil": 954.0,
        "trenzado_al": "36x0.1628",
        "trenzado_acero": "1x0.1628",
        "seccion_total_sqin": 0.7702,
        "seccion_al_sqin": 0.7494,
        "diametro_exterior_in": 1.14,
        "peso_total_lbs_kft": 986.0,
        "peso_al_lbs_kft": 885.4,
        "peso_acero_lbs_kft": 70.2,
        "porcentaje_peso_al": 82.73,
        "porcentaje_peso_acero": 7.27,
        "resistencia_ga2_lbs": 19800.0
      },
      "electricas": {
        "resistencia_dc_20c_ohm_kft": 0.0181,
        "resistencia_ac_25c_ohm_kft": 0.0191,
        "resistencia_ac_75c_ohm_kft": 0.0234,
        "ampacidad_75c_std": 970.0,
        "ampacidad_75c_ex3": 1110.0,
        "radio_medio_generico_ft": 0.0369,
        "reactancia_industrial_ohm_kft": 0.0758,
        "reactancia_capacitiva_mohm_kft": 0.4773
      }
    }
  },
  "Phoenix": {
    "tipo": "ACSR",
    "material": "Al/Ac",
    "seccion_nominal": "954.0",
    "seccion_total_mm2": 508.19,
    "diametro_total_mm": 29.34,
    "peso_unitario_dan_m": 1.5312,
    "coeficiente_dilatacion_1_c": 2.2436460581439632e-05,
    "modulo_elasticidad_dan_mm2": 7541.9,
    "carga_rotura_minima_dan": 10408.3,
    "tension_rotura_minima": 20.48,
    "carga_max_trabajo": 2602.1,
    "tension_max_trabajo": 5.12,
    "norma_fabricacion": "ASTM B232",
    "datos_originales": {
      "tipo_original": "ACSR",
      "mecanicas": {
        "tamano_kcmil": 954.0,
        "trenzado_al": "42x0.1507",
        "trenzado_acero": "7x0.0837",
        "seccion_total_sqin": 0.7877,
        "seccion_al_sqin": 0.7491,
        "diametro_exterior_in": 1.155,
        "peso_total_lbs_kft": 1029.0,
        "peso_al_lbs_kft": 898.5,
        "peso_acero_lbs_kft": 130.5,
        "porcentaje_peso_al": 87.32,
        "porcentaje_peso_acero": 12.88,
        "resistencia_ga2_lbs": 23400.0
      },
      "electricas": {
        "resistencia_dc_20c_ohm_kft": 0.0181,
        "resistencia_ac_25c_ohm_kft": 0.019,
        "resistencia_ac_75c_ohm_kft": 0.0233,
        "ampacidad_75c_std": 975.0,
        "ampacidad_75c_ex3": 1115.0,
        "radio_medio_generico_ft": 0.0378,
        "reactancia_industrial_ohm_kft": 0.0753,
        "reactancia_capacitiva_mohm_kft": 0.4752
      }
    }
  },
  "Corncrake": {
    "tipo": "ACSR",
    "material": "Al/Ac",
    "seccion_nominal": "954.0",
    "seccion_total_mm2": 516.84,
    "diametro_total_mm": 29.59,
    "peso_unitario_dan_m": 1.5922,
    "coeficiente_dilatacion_1_c": 2.2240606665834478e-05,
    "modulo_elasticidad_dan_mm2": 7765.0,
    "carga_rotura_minima_dan": 11386.9,
    "tension_rotura_minima": 22.03,
    "carga_max_trabajo": 2846.7,
    "tension_max_trabajo": 5.51,
    "norma_fabricacion": "ASTM B232",
    "datos_originales": {
      "tipo_original": "ACSR",
      "mecanicas": {
        "tamano_kcmil": 954.0,
        "trenzado_al": "20x0.2144",
        "trenzado_acero": "7x0.0971",
        "seccion_total_sqin": 0.8011,
        "seccion_al_sqin": 0.7482,
        "diametro_exterior_in": 1.165,
        "peso_total_lbs_kft": 1070.0,
        "peso_al_lbs_kft": 894.6,
        "peso_acero_lbs_kft": 175.6,
        "porcentaje_peso_al": 83.61,
        "porcentaje_peso_acero": 16.41,
        "resistencia_ga2_lbs": 25600.0
      },
      "electricas": {
        "resistencia_dc_20c_ohm_kft": 0.0179,
        "resistencia_ac_25c_ohm_kft": 0.0187,
        "resistencia_ac_75c_ohm_kft": 0.0223,
        "ampacidad_75c_std": 1000.0,
        "ampacidad_75c_ex3": 1150.0,
        "radio_medio_generico_ft": 0.038,
        "reactancia_industrial_ohm_kft": 0.0752,
        "reactancia_capacitiva_mohm_kft": 0.4739
      }
    }
  },
  "Rail": {
    "tipo": "ACSR",
    "material": "Al/Ac",
    "seccion_nominal": "954.0",
    "seccion_total_mm2": 516.84,
    "diametro_total_mm": 29.59,
    "peso_unitario_dan_m": 1.5996,
    "coeficiente_dilatacion_1_c": 2.2240606665834478e-05,
    "modulo_elasticidad_dan_mm2": 7765.0,
    "carga_rotura_minima_dan": 11520.3,
    "tension_rotura_minima": 22.29,
    "carga_max_trabajo": 2880.1,
    "tension_max_trabajo": 5.57,
    "norma_fabricacion": "ASTM B232",
    "datos_originales": {
      "tipo_original": "ACSR",
      "mecanicas": {
        "tamano_kcmil": 954.0,
        "trenzado_al": "45x0.1456",
        "trenzado_acero": "7x0.0971",
        "seccion_total_sqin": 0.8011,
        "seccion_al_sqin": 0.7482,
        "diametro_exterior_in": 1.165,
        "peso_total_lbs_kft": 1075.0,
        "peso_al_lbs_kft": 895.0,
        "peso_acero_lbs_kft": 175.6,
        "porcentaje_peso_al": 83.63,
        "porcentaje_peso_acero": 16.33,
        "resistencia_ga2_lbs": 25900.0
      },
      "electricas": {
        "resistencia_dc_20c_ohm_kft": 0.018,
        "resistencia_ac_25c_ohm_kft": 0.0189,
        "resistencia_ac_75c_ohm_kft": 0.0233,
        "ampacidad_75c_std": 975.0,
        "ampacidad_75c_ex3": 1120.0,
        "radio_medio_generico_ft": 0.0384,
        "reactancia_industrial_ohm_kft": 0.0749,
        "reactancia_capacitiva_mohm_kft": 0.4739
      }
    }
  },
  "Phoenix_ACSS": {
    "tipo": "ACSS",
    "material": "Al/Ac",
    "seccion_nominal": "954.0",
    "seccion_total_mm2": 508.19,
    "diametro_total_mm": 29.34,
    "peso_unitario_dan_m": 1.5312,
    "coeficiente_dilatacion_1_c": 2.2436460581439632e-05,
    "modulo_elasticidad_dan_mm2": 7541.9,
    "carga_rotura_minima_dan": 6316.2,
    "tension_rotura_minima": 12.43,
    "carga_max_trabajo": 1579.0,
    "tension_max_trabajo": 3.11,
    "norma_fabricacion": "ASTM B856",
    "datos_originales": {
      "tipo_original": "ACSS",
      "mecanicas": {
        "tamano_kcmil": 954.0,
        "trenzado_al": "42x0.1507",
        "trenzado_acero": "7x0.0837",
        "seccion_total_sqin": 0.7877,
        "seccion_al_sqin": 0.7491,
        "diametro_exterior_in": 1.155,
        "peso_total_lbs_kft": 1029.0,
        "peso_al_lbs_kft": 898.5,
        "peso_acero_lbs_kft": 130.5,
        "porcentaje_peso_al": 87.32,
        "porcentaje_peso_acero": 12.68,
        "resistencia_ma2_lbs": 14200.0
      },
      "electricas": {
        "resistencia_dc_20c_ohm_kft": 0.0176,
        "resistencia_ac_25c_ohm_kft": 0.0185,
        "resistencia_ac_75c_ohm_kft": 0.0228,
        "ampacidad_75c_std": 985.0,
        "ampacidad_75c_ex3": 1130.0,
        "radio_medio_generico_ft": 0.0378,
        "reactancia_industrial_ohm_kft": 0.0753,
        "reactancia_capacitiva_mohm_kft": 0.4752,
        "resistencia_ac_200c": 0.033
      }
    }
  },
  "Corncrake_ACSS": {
    "tipo": "ACSS",
    "material": "Al/Ac",
    "seccion_nominal": "954.0",
    "seccion_total_mm2": 516.84,
    "diametro_total_mm": 29.59,
    "peso_unitario_dan_m": 1.5922,
    "coeficiente_dilatacion_1_c": 2.2254961927349895e-05,
    "modulo_elasticidad_dan_mm2": 7748.7,
    "carga_rotura_minima_dan": 7428.2,
    "tension_rotura_minima": 14.37,
    "carga_max_trabajo": 1857.0,
    "tension_max_trabajo": 3.59,
    "norma_fabricacion": "ASTM B856",
    "datos_originales": {
      "tipo_original": "ACSS",
      "mecanicas": {
        "tamano_kcmil": 954.0,
        "trenzado_al": "20x0.2184",
        "trenzado_acero": "7x0.0971",
        "seccion_total_sqin": 0.8011,
        "seccion_al_sqin": 0.7492,
        "diametro_exterior_in": 1.165,
        "peso_total_lbs_kft": 1070.0,
        "peso_al_lbs_kft": 894.6,
        "peso_acero_lbs_kft": 175.6,
        "porcentaje_peso_al": 83.61,
        "porcentaje_peso_acero": 16.41,
        "resistencia_ma2_lbs": 16700.0
      },
      "electricas": {
        "resistencia_dc_20c_ohm_kft": 0.0174,
        "resistencia_ac_25c_ohm_kft": 0.0182,
        "resistencia_ac_75c_ohm_kft": 0.0218,
        "ampacidad_75c_std": 1010.0,
        "ampacidad_75c_ex3": 1160.0,
        "radio_medio_generico_ft": 0.038,
        "reactancia_industrial_ohm_kft": 0.0752,
        "reactancia_capacitiva_mohm_kft": 0.4739,
        "resistencia_ac_200c": 0.0307
      }
    }
  },
  "Rail_ACSS": {
    "tipo": "ACSS",
    "material": "Al/Ac",
    "seccion_nominal": "954.0",
    "seccion_total_mm2": 516.84,
    "diametro_total_mm": 29.59,
    "peso_unitario_dan_m": 1.5996,
    "coeficiente_dilatacion_1_c": 2.2254961927349895e-05,
    "modulo_elasticidad_dan_mm2": 7748.7,
    "carga_rotura_minima_dan": 7428.2,
    "tension_rotura_minima": 14.37,
    "carga_max_trabajo": 1857.0,
    "tension_max_trabajo": 3.59,
    "norma_fabricacion": "ASTM B856",
    "datos_originales": {
      "tipo_original": "ACSS",
      "mecanicas": {
        "tamano_kcmil": 954.0,
        "trenzado_al": "45x0.1456",
        "trenzado_acero": "7x0.0971",
        "seccion_total_sqin": 0.8011,
        "seccion_al_sqin": 0.7492,
        "diametro_exterior_in": 1.165,
        "peso_total_lbs_kft": 1075.0,
        "peso_al_lbs_kft": 899.0,
        "peso_acero_lbs_kft": 175.6,
        "porcentaje_peso_al": 83.63,
        "porcentaje_peso_acero": 16.33,
        "resistencia_ma2_lbs": 16700.0
      },
      "electricas": {
        "resistencia_dc_20c_ohm_kft": 0.0175,
        "resistencia_ac_25c_ohm_kft": 0.0184,
        "resistencia_ac_75c_ohm_kft": 0.0227,
        "ampacidad_75c_std": 990.0,
        "ampacidad_75c_ex3": 1135.0,
        "radio_medio_generico_ft": 0.0384,
        "reactancia_industrial_ohm_kft": 0.0749,
        "reactancia_capacitiva_mohm_kft": 0.4739,
        "resistencia_ac_200c": 0.0329
      }
    }
  }
}